[{"id":"f2220e44.6bfb4","type":"tab","label":"Flow 1","disabled":false,"info":""},{"id":"96a6cce3.d0aa7","type":"server","name":"Home Assistant","addon":true},{"id":"22b6d374.a6a58c","type":"ha-zone","z":"f2220e44.6bfb4","server":"96a6cce3.d0aa7","name":"Enter Shopping (Philipp)","exposeToHomeAssistant":false,"haConfig":[{"property":"name","value":""},{"property":"icon","value":""}],"entities":["device_tracker.sm_g955f","device_tracker.philipp_iphone8"],"event":"enter","zones":["shopping"],"x":230,"y":240,"wires":[["d0417779.510df8","1cf38a77.1943f6"]]},{"id":"d0417779.510df8","type":"api-call-service","z":"f2220e44.6bfb4","name":"Notify family","server":"96a6cce3.d0aa7","version":1,"debugenabled":false,"service_domain":"notify","service":"mobile_app_sm_g950f","entityId":"","data":"","dataType":"json","mergecontext":"","output_location":"","output_location_type":"none","mustacheAltTags":false,"x":530,"y":240,"wires":[[]]},{"id":"1cf38a77.1943f6","type":"delay","z":"f2220e44.6bfb4","name":"","pauseType":"delay","timeout":"5","timeoutUnits":"minutes","rate":"1","nbRateUnits":"1","rateUnits":"second","randomFirst":"1","randomLast":"5","randomUnits":"seconds","drop":false,"x":400,"y":340,"wires":[["d0417779.510df8"]]}]